{
 "account": "0xD2725bfEC6C67b3ef943550DE1d947959Ea1B05E",
 "counts": {
  "fills": 0,
  "funding": 24,
  "ledger": 0
 },
 "day_utc": "2026-06-15",
 "fills": [],
 "funding": [
  {
   "delta": {
    "coin": "ENA",
    "fundingRate": "0.0000125",
    "nSamples": null,
    "szi": "-317.0",
    "type": "funding",
    "usdc": "0.000333"
   },
   "hash": "0x0000000000000000000000000000000000000000000000000000000000000000",
   "time": 1781481600049
  },
  {
   "delta": {
    "coin": "ENA",
    "fundingRate": "0.0000125",
    "nSamples": null,
    "szi": "-317.0",
    "type": "funding",
    "usdc": "0.000331"
   },
   "hash": "0x0000000000000000000000000000000000000000000000000000000000000000",
   "time": 1781485200042
  },
  {
   "delta": {
    "coin": "ENA",
    "fundingRate": "0.0000125",
    "nSamples": null,
    "szi": "-317.0",
    "type": "funding",
    "usdc": "0.000332"
   },
   "hash": "0x0000000000000000000000000000000000000000000000000000000000000000",
   "time": 1781488800063
  },
  {
   "delta": {
    "coin": "ENA",
    "fundingRate": "0.0000125",
    "nSamples": null,
    "szi": "-317.0",
    "type": "funding",
    "usdc": "0.000333"
   },
   "hash": "0x0000000000000000000000000000000000000000000000000000000000000000",
   "time": 1781492400033
  },
  {
   "delta": {
    "coin": "ENA",
    "fundingRate": "0.0000125",
    "nSamples": null,
    "szi": "-317.0",
    "type": "funding",
    "usdc": "0.000332"
   },
   "hash": "0x0000000000000000000000000000000000000000000000000000000000000000",
   "time": 1781496000023
  },
  {
   "delta": {
    "coin": "ENA",
    "fundingRate": "0.0000125",
    "nSamples": null,
    "szi": "-317.0",
    "type": "funding",
    "usdc": "0.000334"
   },
   "hash": "0x0000000000000000000000000000000000000000000000000000000000000000",
   "time": 1781499600034
  },
  {
   "delta": {
    "coin": "ENA",
    "fundingRate": "0.0000125",
    "nSamples": null,
    "szi": "-317.0",
    "type": "funding",
    "usdc": "0.000344"
   },
   "hash": "0x0000000000000000000000000000000000000000000000000000000000000000",
   "time": 1781503200000
  },
  {
   "delta": {
    "coin": "ENA",
    "fundingRate": "0.0000125",
    "nSamples": null,
    "szi": "-317.0",
    "type": "funding",
    "usdc": "0.000339"
   },
   "hash": "0x0000000000000000000000000000000000000000000000000000000000000000",
   "time": 1781506800033
  },
  {
   "delta": {
    "coin": "ENA",
    "fundingRate": "0.0000125",
    "nSamples": null,
    "szi": "-317.0",
    "type": "funding",
    "usdc": "0.000338"
   },
   "hash": "0x0000000000000000000000000000000000000000000000000000000000000000",
   "time": 1781510400043
  },
  {
   "delta": {
    "coin": "ENA",
    "fundingRate": "0.0000125",
    "nSamples": null,
    "szi": "-317.0",
    "type": "funding",
    "usdc": "0.000338"
   },
   "hash": "0x0000000000000000000000000000000000000000000000000000000000000000",
   "time": 1781514000039
  },
  {
   "delta": {
    "coin": "ENA",
    "fundingRate": "0.0000125",
    "nSamples": null,
    "szi": "-317.0",
    "type": "funding",
    "usdc": "0.000339"
   },
   "hash": "0x0000000000000000000000000000000000000000000000000000000000000000",
   "time": 1781517600048
  },
  {
   "delta": {
    "coin": "ENA",
    "fundingRate": "0.0000125",
    "nSamples": null,
    "szi": "-317.0",
    "type": "funding",
    "usdc": "0.000347"
   },
   "hash": "0x0000000000000000000000000000000000000000000000000000000000000000",
   "time": 1781521200029
  },
  {
   "delta": {
    "coin": "ENA",
    "fundingRate": "0.0000125",
    "nSamples": null,
    "szi": "-317.0",
    "type": "funding",
    "usdc": "0.000344"
   },
   "hash": "0x0000000000000000000000000000000000000000000000000000000000000000",
   "time": 1781524800000
  },
  {
   "delta": {
    "coin": "ENA",
    "fundingRate": "0.0000125",
    "nSamples": null,
    "szi": "-317.0",
    "type": "funding",
    "usdc": "0.000346"
   },
   "hash": "0x0000000000000000000000000000000000000000000000000000000000000000",
   "time": 1781528400063
  },
  {
   "delta": {
    "coin": "ENA",
    "fundingRate": "0.0000125",
    "nSamples": null,
    "szi": "-317.0",
    "type": "funding",
    "usdc": "0.000352"
   },
   "hash": "0x0000000000000000000000000000000000000000000000000000000000000000",
   "time": 1781532000031
  },
  {
   "delta": {
    "coin": "ENA",
    "fundingRate": "0.0000125",
    "nSamples": null,
    "szi": "-317.0",
    "type": "funding",
    "usdc": "0.000351"
   },
   "hash": "0x0000000000000000000000000000000000000000000000000000000000000000",
   "time": 1781535600041
  },
  {
   "delta": {
    "coin": "ENA",
    "fundingRate": "0.0000125",
    "nSamples": null,
    "szi": "-317.0",
    "type": "funding",
    "usdc": "0.000355"
   },
   "hash": "0x0000000000000000000000000000000000000000000000000000000000000000",
   "time": 1781539200005
  },
  {
   "delta": {
    "coin": "ENA",
    "fundingRate": "0.0000125",
    "nSamples": null,
    "szi": "-317.0",
    "type": "funding",
    "usdc": "0.000352"
   },
   "hash": "0x0000000000000000000000000000000000000000000000000000000000000000",
   "time": 1781542800050
  },
  {
   "delta": {
    "coin": "ENA",
    "fundingRate": "0.0000125",
    "nSamples": null,
    "szi": "-317.0",
    "type": "funding",
    "usdc": "0.00035"
   },
   "hash": "0x0000000000000000000000000000000000000000000000000000000000000000",
   "time": 1781546400012
  },
  {
   "delta": {
    "coin": "ENA",
    "fundingRate": "0.0000125",
    "nSamples": null,
    "szi": "-317.0",
    "type": "funding",
    "usdc": "0.000346"
   },
   "hash": "0x0000000000000000000000000000000000000000000000000000000000000000",
   "time": 1781550000021
  },
  {
   "delta": {
    "coin": "ENA",
    "fundingRate": "0.0000125",
    "nSamples": null,
    "szi": "-317.0",
    "type": "funding",
    "usdc": "0.00034"
   },
   "hash": "0x0000000000000000000000000000000000000000000000000000000000000000",
   "time": 1781553600038
  },
  {
   "delta": {
    "coin": "ENA",
    "fundingRate": "-0.0000077831",
    "nSamples": null,
    "szi": "-317.0",
    "type": "funding",
    "usdc": "-0.000213"
   },
   "hash": "0x0000000000000000000000000000000000000000000000000000000000000000",
   "time": 1781557200032
  },
  {
   "delta": {
    "coin": "ENA",
    "fundingRate": "0.0000125",
    "nSamples": null,
    "szi": "-317.0",
    "type": "funding",
    "usdc": "0.000341"
   },
   "hash": "0x0000000000000000000000000000000000000000000000000000000000000000",
   "time": 1781560800024
  },
  {
   "delta": {
    "coin": "ENA",
    "fundingRate": "-0.000049391",
    "nSamples": null,
    "szi": "-317.0",
    "type": "funding",
    "usdc": "-0.001324"
   },
   "hash": "0x0000000000000000000000000000000000000000000000000000000000000000",
   "time": 1781564400029
  }
 ],
 "generated_at": "2026-06-16T00:10:15Z",
 "ledger_updates": [],
 "schema": "combo_g_trackrecord.daily_export.v1",
 "source": "api.hyperliquid.xyz/info (public, read-only)",
 "window_ms": [
  1781481600000,
  1781568000000
 ]
}